http_query/__init__.py
http_query/http_query.py
bh_25_req_ase-0.0.3.dist-info/METADATA
bh_25_req_ase-0.0.3.dist-info/WHEEL
bh_25_req_ase-0.0.3.dist-info/entry_points.txt
bh_25_req_ase-0.0.3.dist-info/top_level.txt
bh_25_req_ase-0.0.3.dist-info/RECORD
